MANIFEST.in
README.txt
import_file.py
setup.py
setup_and_test.cmd
import_file.egg-info/PKG-INFO
import_file.egg-info/SOURCES.txt
import_file.egg-info/dependency_links.txt
import_file.egg-info/top_level.txt
test/test_import_file.py
test/stub_package/__init__.py