Metadata-Version: 1.0
Name: import-file
Version: 1.11
Summary: Import py files using their relative or absolute path.
Home-page: UNKNOWN
Author: Yuval Greenfield
Author-email: ubershmekel@gmail.com
License: Public Domain
Keywords: import,path,file
Platform: UNKNOWN
Classifier: Development Status :: 4 - Beta
Classifier: Environment :: Console
Classifier: Intended Audience :: Developers
Classifier: Operating System :: OS Independent
Classifier: Programming Language :: Python :: 2
Classifier: Programming Language :: Python :: 3
Classifier: Topic :: Utilities
Classifier: Topic :: Software Development :: Libraries :: Python Modules
Classifier: Topic :: Terminals
